pleroma_bot/__init__.py
pleroma_bot/_cohost.py
pleroma_bot/_error.py
pleroma_bot/_misskey.py
pleroma_bot/_pin.py
pleroma_bot/_pleroma.py
pleroma_bot/_processing.py
pleroma_bot/_twitter.py
pleroma_bot/_utils.py
pleroma_bot/cli.py
pleroma_bot/i18n.py
pleroma_bot/locale/pleroma_bot.pot
pleroma_bot/locale/es/LC_MESSAGES/pleroma_bot.mo
pleroma_bot/locale/es/LC_MESSAGES/pleroma_bot.po
pleroma_bot/locale/es_ES/LC_MESSAGES/pleroma_bot.mo
pleroma_bot/locale/es_ES/LC_MESSAGES/pleroma_bot.po
pleroma_bot-1.2.0.dist-info/LICENSE.md
pleroma_bot-1.2.0.dist-info/METADATA
pleroma_bot-1.2.0.dist-info/WHEEL
pleroma_bot-1.2.0.dist-info/entry_points.txt
pleroma_bot-1.2.0.dist-info/top_level.txt
pleroma_bot-1.2.0.dist-info/RECORD
