Metadata-Version: 2.1
Name: pleroma-bot
Version: 1.2.0
Summary: Mirror one or multiple Twitter accounts in Pleroma/Mastodon
Home-page: https://github.com/robertoszek/pleroma-bot
Author: Roberto Chamorro
Author-email: robertoszek@robertoszek.xyz
Project-URL: Documentation, https://robertoszek.github.io/pleroma-bot
Classifier: Environment :: Console
Classifier: Programming Language :: Python :: 3
Classifier: License :: OSI Approved :: MIT License
Classifier: Operating System :: OS Independent
Requires-Python: >=3.6
License-File: LICENSE.md
Requires-Dist: requests (>=2.24.0)
Requires-Dist: PyYAML (>=5.3.1)
Requires-Dist: requests-oauthlib (>=1.3.0)
Requires-Dist: feedparser (>=6.0.10)
Requires-Dist: beautifulsoup4 (>=4.9.3)
Requires-Dist: tqdm (>=4.64.1)
Provides-Extra: lint
Requires-Dist: flake8 ; extra == 'lint'
Requires-Dist: flake8-quotes ; extra == 'lint'
Provides-Extra: test
Requires-Dist: tox ; extra == 'test'
Requires-Dist: pytest ; extra == 'test'
Requires-Dist: requests-mock ; extra == 'test'
Requires-Dist: pytest-cov ; extra == 'test'
Requires-Dist: python-magic-bin ; (platform_system == "Windows") and extra == 'test'
